antchain_sdk_ak_8146025f0aa2474a88d81f508253e029/__init__.py
antchain_sdk_ak_8146025f0aa2474a88d81f508253e029/client.py
antchain_sdk_ak_8146025f0aa2474a88d81f508253e029/models.py
antchain_ak_8146025f0aa2474a88d81f508253e029-1.0.4.dist-info/LICENSE
antchain_ak_8146025f0aa2474a88d81f508253e029-1.0.4.dist-info/METADATA
antchain_ak_8146025f0aa2474a88d81f508253e029-1.0.4.dist-info/WHEEL
antchain_ak_8146025f0aa2474a88d81f508253e029-1.0.4.dist-info/top_level.txt
antchain_ak_8146025f0aa2474a88d81f508253e029-1.0.4.dist-info/RECORD
